{
  "type": "Feature",
  "properties": {
    "gn:gn_country":"IM",
    "gn:gn_fcode":"PPL",
    "gn:gn_pop":0,
    "iso:country":"IM",
    "name:unk_x_variant":[
        "Saint Anne"
    ],
    "qs_pg:aaroncc":"IM",
    "qs_pg:gn_country":"IM",
    "qs_pg:gn_fcode":"PPL",
    "qs_pg:gn_pop":0,
    "qs_pg:name":"Santon",
    "qs_pg:name_adm0":"United Kingdom",
    "qs_pg:name_adm1":"Isle of Man",
    "qs_pg:photos":145,
    "qs_pg:photos_1k":29,
    "qs_pg:photos_9k":1,
    "qs_pg:photos_9r":3,
    "qs_pg:photos_all":145,
    "qs_pg:photos_sr":3,
    "qs_pg:pop_sr":0,
    "qs_pg:qs_pg_placetype":"locality",
    "qs_pg:qs_pg_placetype_gp":"Town",
    "qs_pg:woe_adm0":23424975,
    "woe:adm0_id":23424975,
    "woe:name_adm0":"United Kingdom",
    "woe:name_adm1":"Isle of Man",
    "woe:placetype":"Town",
    "wof:name":"Santon",
    "wof:placetype":"locality"
},
  "geometry": {"coordinates":[-4.58333,54.11667],"type":"Point"}
}