{
  "type": "Feature",
  "properties": {
    "iso:country":"IM",
    "qs_pg:aaroncc":"IM",
    "qs_pg:name":"Dhoor",
    "qs_pg:name_adm0":"United Kingdom",
    "qs_pg:name_adm1":"Isle of Man",
    "qs_pg:photos":16,
    "qs_pg:photos_1k":3,
    "qs_pg:photos_9k":1,
    "qs_pg:photos_9r":1,
    "qs_pg:photos_all":16,
    "qs_pg:photos_sr":1,
    "qs_pg:pop_sr":0,
    "qs_pg:qs_pg_placetype":"locality",
    "qs_pg:qs_pg_placetype_gp":"Town",
    "qs_pg:woe_adm0":23424975,
    "woe:adm0_id":23424975,
    "woe:name_adm0":"United Kingdom",
    "woe:name_adm1":"Isle of Man",
    "woe:placetype":"Town",
    "wof:name":"Dhoor",
    "wof:placetype":"locality"
},
  "geometry": {"coordinates":[-4.385,54.337211],"type":"Point"}
}