{
  "type": "Feature",
  "properties": {
    "gn:gn_country":"IM",
    "gn:gn_fcode":"PPL",
    "gn:gn_pop":0,
    "iso:country":"IM",
    "name:eng_x_preferred":[
        "Union Mills"
    ],
    "name:fra_x_preferred":[
        "Union Mills"
    ],
    "name:glv_x_preferred":[
        "Mwyllin Doo Aah"
    ],
    "name:hun_x_preferred":[
        "Union Mills"
    ],
    "name:nld_x_preferred":[
        "Union Mills"
    ],
    "name:slk_x_preferred":[
        "Union Mills"
    ],
    "qs_pg:aaroncc":"IM",
    "qs_pg:gn_country":"IM",
    "qs_pg:gn_fcode":"PPL",
    "qs_pg:gn_pop":0,
    "qs_pg:name":"Union Mills",
    "qs_pg:name_adm0":"United Kingdom",
    "qs_pg:name_adm1":"Isle of Man",
    "qs_pg:photos":356,
    "qs_pg:photos_1k":72,
    "qs_pg:photos_9k":2,
    "qs_pg:photos_9r":5,
    "qs_pg:photos_all":356,
    "qs_pg:photos_sr":6,
    "qs_pg:pop_sr":0,
    "qs_pg:qs_pg_placetype":"locality",
    "qs_pg:qs_pg_placetype_gp":"Town",
    "qs_pg:woe_adm0":23424975,
    "woe:adm0_id":23424975,
    "woe:name_adm0":"United Kingdom",
    "woe:name_adm1":"Isle of Man",
    "woe:placetype":"Town",
    "wof:name":"Union Mills",
    "wof:placetype":"locality"
},
  "geometry": {"coordinates":[-4.52019,54.16957],"type":"Point"}
}