{
  "type": "Feature",
  "properties": {
    "iso:country":"IM",
    "name:eng_x_preferred":[
        "Ronague"
    ],
    "name:eus_x_preferred":[
        "Ronague"
    ],
    "name:glv_x_preferred":[
        "Ronnag"
    ],
    "name:nld_x_preferred":[
        "Ronague"
    ],
    "qs_pg:aaroncc":"IM",
    "qs_pg:name":"Ronague",
    "qs_pg:name_adm0":"United Kingdom",
    "qs_pg:name_adm1":"Isle of Man",
    "qs_pg:photos":21,
    "qs_pg:photos_1k":4,
    "qs_pg:photos_9k":1,
    "qs_pg:photos_9r":1,
    "qs_pg:photos_all":21,
    "qs_pg:photos_sr":1,
    "qs_pg:pop_sr":0,
    "qs_pg:qs_pg_placetype":"locality",
    "qs_pg:qs_pg_placetype_gp":"Town",
    "qs_pg:woe_adm0":23424975,
    "woe:adm0_id":23424975,
    "woe:name_adm0":"United Kingdom",
    "woe:name_adm1":"Isle of Man",
    "woe:placetype":"Town",
    "wof:name":"Ronague",
    "wof:placetype":"locality"
},
  "geometry": {"coordinates":[-4.681833,54.113559],"type":"Point"}
}