{
  "type": "Feature",
  "properties": {
    "iso:country":"IM",
    "qs_pg:aaroncc":"IM",
    "qs_pg:name":"Dreemskerry",
    "qs_pg:name_adm0":"United Kingdom",
    "qs_pg:name_adm1":"Isle of Man",
    "qs_pg:photos":9,
    "qs_pg:photos_1k":2,
    "qs_pg:photos_9k":1,
    "qs_pg:photos_9r":1,
    "qs_pg:photos_all":9,
    "qs_pg:photos_sr":1,
    "qs_pg:pop_sr":0,
    "qs_pg:qs_pg_placetype":"locality",
    "qs_pg:qs_pg_placetype_gp":"Town",
    "qs_pg:woe_adm0":23424975,
    "woe:adm0_id":23424975,
    "woe:name_adm0":"United Kingdom",
    "woe:name_adm1":"Isle of Man",
    "woe:placetype":"Town",
    "wof:name":"Dreemskerry",
    "wof:placetype":"locality"
},
  "geometry": {"coordinates":[-4.340865,54.293345],"type":"Point"}
}