{
  "type": "Feature",
  "properties": {
    "iso:country":"IM",
    "name:eng_x_preferred":[
        "Barregarrow"
    ],
    "name:eus_x_preferred":[
        "Barregarrow"
    ],
    "name:fra_x_preferred":[
        "Barregarrow"
    ],
    "name:glv_x_preferred":[
        "Bayr Garroo"
    ],
    "name:nld_x_preferred":[
        "Barregarrow"
    ],
    "qs_pg:aaroncc":"IM",
    "qs_pg:name":"Barregarrow",
    "qs_pg:name_adm0":"United Kingdom",
    "qs_pg:name_adm1":"Isle of Man",
    "qs_pg:photos":116,
    "qs_pg:photos_1k":24,
    "qs_pg:photos_9k":1,
    "qs_pg:photos_9r":3,
    "qs_pg:photos_all":116,
    "qs_pg:photos_sr":3,
    "qs_pg:pop_sr":0,
    "qs_pg:qs_pg_placetype":"locality",
    "qs_pg:qs_pg_placetype_gp":"Town",
    "qs_pg:woe_adm0":23424975,
    "woe:adm0_id":23424975,
    "woe:name_adm0":"United Kingdom",
    "woe:name_adm1":"Isle of Man",
    "woe:placetype":"Town",
    "wof:name":"Barregarrow",
    "wof:placetype":"locality"
},
  "geometry": {"coordinates":[-4.533614,54.260862],"type":"Point"}
}