{
  "type": "Feature",
  "properties": {
    "iso:country":"IM",
    "name:eng_x_preferred":[
        "Strang"
    ],
    "name:eus_x_preferred":[
        "Strang"
    ],
    "name:fra_x_preferred":[
        "Strang"
    ],
    "name:glv_x_preferred":[
        "Yn Strang"
    ],
    "name:nld_x_preferred":[
        "Strang"
    ],
    "qs_pg:aaroncc":"IM",
    "qs_pg:name":"Strang",
    "qs_pg:name_adm0":"United Kingdom",
    "qs_pg:name_adm1":"Isle of Man",
    "qs_pg:photos":15,
    "qs_pg:photos_1k":3,
    "qs_pg:photos_9k":1,
    "qs_pg:photos_9r":1,
    "qs_pg:photos_all":15,
    "qs_pg:photos_sr":1,
    "qs_pg:pop_sr":0,
    "qs_pg:qs_pg_placetype":"locality",
    "qs_pg:qs_pg_placetype_gp":"Town",
    "qs_pg:woe_adm0":23424975,
    "woe:adm0_id":23424975,
    "woe:name_adm0":"United Kingdom",
    "woe:name_adm1":"Isle of Man",
    "woe:placetype":"Town",
    "wof:name":"Strang",
    "wof:placetype":"locality"
},
  "geometry": {"coordinates":[-4.510402,54.174618],"type":"Point"}
}