{
  "type": "Feature",
  "properties": {
    "gn:admin1_code":"00",
    "gn:asciiname":"Ronaldsway",
    "gn:country_code":"IM",
    "gn:dem":7,
    "gn:feature_class":"P",
    "gn:feature_code":"PPL",
    "gn:name":"Ronaldsway",
    "gn:population":0,
    "gn:timezone":"Europe/Isle_of_Man",
    "iso:country":"IM",
    "name:fra_x_preferred":[
        "Ronaldsway"
    ],
    "name:glv_x_preferred":[
        "Roonysvaie"
    ],
    "name:nld_x_preferred":[
        "Ronaldsway"
    ],
    "name:nor_x_preferred":[
        "Ronaldsway"
    ],
    "name:swe_x_preferred":[
        "Ronaldsway"
    ],
    "wof:name":"Ronaldsway",
    "wof:placetype":"locality"
},
  "geometry": {"coordinates":[-4.61667,54.08333],"type":"Point"}
}